convertcurl/__init__.py
convertcurl-0.0.7.dist-info/METADATA
convertcurl-0.0.7.dist-info/WHEEL
convertcurl-0.0.7.dist-info/entry_points.txt
convertcurl-0.0.7.dist-info/top_level.txt
convertcurl-0.0.7.dist-info/RECORD
