Metadata-Version: 2.1
Name: convertcurl
Version: 0.0.7
Summary: 把curl命令转换成requests或者scrapy的请求，支持chrome和charles格式
Home-page: https://github.com/mathgo
Author: golmic
Author-email: ljq0225@gmail.com
License: UNKNOWN
Platform: UNKNOWN
